dupe_remove/__init__.py
dupe_remove/__init__.pyc
dupe_remove/_version.py
dupe_remove/_version.pyc
dupe_remove/handler.py
dupe_remove/logger.py
dupe_remove/scheduler.py
dupe_remove/worker.py
dupe_remove/__pycache__/__init__.cpython-36.pyc
dupe_remove/__pycache__/_version.cpython-36.pyc
dupe_remove/__pycache__/handler.cpython-36.pyc
dupe_remove/__pycache__/logger.cpython-36.pyc
dupe_remove/__pycache__/scheduler.cpython-36.pyc
dupe_remove/__pycache__/worker.cpython-36.pyc
dupe_remove/docs/__init__.py
dupe_remove/handlers/__init__.py
dupe_remove/handlers/postgres.py
dupe_remove/handlers/redshift.py
dupe_remove/tests/__init__.py
dupe_remove/tests/with_postgres.py
dupe_remove/tests/with_redshift.py
dupe_remove/tests/__pycache__/__init__.cpython-36.pyc
dupe_remove/tests/__pycache__/with_postgres.cpython-36.pyc
dupe_remove/tests/__pycache__/with_redshift.cpython-36.pyc
dupe_remove-0.0.1.dist-info/AUTHORS.rst
dupe_remove-0.0.1.dist-info/LICENSE.txt
dupe_remove-0.0.1.dist-info/METADATA
dupe_remove-0.0.1.dist-info/WHEEL
dupe_remove-0.0.1.dist-info/entry_points.txt
dupe_remove-0.0.1.dist-info/top_level.txt
dupe_remove-0.0.1.dist-info/RECORD
